excels2vensim/__init__.py
excels2vensim/__main__.py
excels2vensim/_version.py
excels2vensim/excels2vensim.py
excels2vensim/cli/__init__.py
excels2vensim/cli/main.py
excels2vensim/cli/parser.py
excels2vensim/gui/__init__.py
excels2vensim/gui/gui.py
excels2vensim/utils/__init__.py
excels2vensim/utils/excels.py
excels2vensim/utils/subscript_parser.py
excels2vensim/utils/subscripts.py
excels2vensim-0.14.0.dist-info/LICENSE
excels2vensim-0.14.0.dist-info/METADATA
excels2vensim-0.14.0.dist-info/WHEEL
excels2vensim-0.14.0.dist-info/top_level.txt
excels2vensim-0.14.0.dist-info/RECORD
