Metadata-Version: 2.1
Name: excels2vensim
Version: 0.14.0
Summary: Easy write excel inputs in Vensim
Home-page: https://github.com/SDXorg/excels2vensim
Author: Eneko Martin Martinez
Author-email: eneko.martin.martinez@gmail.com
License: MIT
Keywords: System Dynamics,Vensim,Excel
Platform: UNKNOWN
Classifier: Development Status :: 3 - Alpha
Classifier: Topic :: Scientific/Engineering :: Information Analysis
Classifier: Intended Audience :: Science/Research
Classifier: License :: OSI Approved :: MIT License
Classifier: Programming Language :: Python :: 3.9
Classifier: Programming Language :: Python :: 3.10
Classifier: Programming Language :: Python :: 3.11
Requires-Python: >=3.9
License-File: LICENSE
Requires-Dist: pysd >=3.12
